ristpy/__init__.py
ristpy/__main__.py
ristpy/walkers.py
RistLang-1.2.1.dist-info/LICENSE
RistLang-1.2.1.dist-info/METADATA
RistLang-1.2.1.dist-info/WHEEL
RistLang-1.2.1.dist-info/entry_points.txt
RistLang-1.2.1.dist-info/top_level.txt
RistLang-1.2.1.dist-info/RECORD
