Metadata-Version: 2.1
Name: RistLang
Version: 1.2.1
Summary: A module for compiling RistLang
Home-page: https://github.com/RistPy/PyRist
License: MIT
Project-URL: Issue tracker, https://github.com/RistPy/PyRist/issues
Classifier: Programming Language :: Python
Classifier: Programming Language :: Python :: 3.8
Classifier: Programming Language :: Python :: 3.9
Classifier: Programming Language :: Python :: 3.10
Classifier: Programming Language :: Python :: 3.11
Classifier: License :: OSI Approved :: MIT License
Classifier: Operating System :: OS Independent
Requires-Python: >=3.8
License-File: LICENSE
Requires-Dist: import-expression
